spimind/__init__.py
spimind/backends.py
spimind/core.py
spimind-0.1.0.dist-info/LICENSE
spimind-0.1.0.dist-info/METADATA
spimind-0.1.0.dist-info/WHEEL
spimind-0.1.0.dist-info/top_level.txt
spimind-0.1.0.dist-info/RECORD
