Metadata-Version: 2.2
Name: spimind
Version: 0.1.0
Summary: Event stream logging system for Spiking Neural Networks
Home-page: https://github.com/mini-mind/spimind
Author: Spimind Team
Author-email: Spimind Team <team@spimind.dev>
License: MIT
Project-URL: Homepage, https://github.com/mini-mind/spimind
Project-URL: Repository, https://github.com/mini-mind/spimind
Project-URL: Documentation, https://github.com/mini-mind/spimind#readme
Project-URL: Issues, https://github.com/mini-mind/spimind/issues
Classifier: Development Status :: 3 - Alpha
Classifier: Intended Audience :: Science/Research
Classifier: License :: OSI Approved :: MIT License
Classifier: Operating System :: OS Independent
Classifier: Programming Language :: Python :: 3
Classifier: Programming Language :: Python :: 3.8
Classifier: Programming Language :: Python :: 3.9
Classifier: Programming Language :: Python :: 3.10
Classifier: Programming Language :: Python :: 3.11
Classifier: Topic :: Scientific/Engineering :: Artificial Intelligence
Requires-Python: >=3.8
License-File: LICENSE
Requires-Dist: tinydb>=4.0.0
Dynamic: author
Dynamic: home-page
Dynamic: requires-python
